srpskiwn/__init__.py
srpskiwn/srppolsets.py
srpskiwn/srpskiwordnet.py
srpskiwordnet-0.1.dist-info/LICENSE
srpskiwordnet-0.1.dist-info/METADATA
srpskiwordnet-0.1.dist-info/WHEEL
srpskiwordnet-0.1.dist-info/top_level.txt
srpskiwordnet-0.1.dist-info/RECORD
