Metadata-Version: 2.1
Name: srpskiwordnet
Version: 0.1
Summary: NLTK interface for Serbian Wordnet
Home-page: https://github.com/sasa5linkar/Srpski-Wordenet-Python-wrapper
Author: Petalinkar Saša
Author-email: sasa5linkar@gmial.com
License: UNKNOWN
Platform: UNKNOWN
Classifier: Programming Language :: Python :: 3
Classifier: License :: OSI Approved :: MIT License
Classifier: Operating System :: OS Independent
Requires-Python: >=3.7
Requires-Dist: requests
Requires-Dist: nltk
Requires-Dist: pandas
Requires-Dist: scikit-learn
